pulse/__init__.py
pulse/main.py
pulse/plot.py
pulse/sections/__init__.py
pulse/sections/battery.py
pulse/sections/cpu.py
pulse/sections/memory.py
pulse/sections/network.py
pulse/sections/processes.py
pulse/sections/storage.py
pulse_system_monitor-0.1.2.dist-info/METADATA
pulse_system_monitor-0.1.2.dist-info/WHEEL
pulse_system_monitor-0.1.2.dist-info/entry_points.txt
pulse_system_monitor-0.1.2.dist-info/licenses/LICENSE
pulse_system_monitor-0.1.2.dist-info/RECORD
