Metadata-Version: 2.4
Name: pulse-system-monitor
Version: 0.1.2
Summary: A cross-platform, TUI system monitor.
Project-URL: Repository, https://github.com/harshdeep-rakkar/pulse
Author-email: Harshdeep Singh <harshdeep.s.rakkar@gmail.com>
License: MIT
License-File: LICENSE
Classifier: Environment :: Console
Classifier: Operating System :: OS Independent
Classifier: Programming Language :: Python :: 3
Classifier: Topic :: System :: Monitoring
Requires-Python: >=3.13
Requires-Dist: plotext>=5.3.2
Requires-Dist: psutil>=7.1.3
Requires-Dist: textual>=6.8.0
